README
setup.py
interact/__init__.py
interact/cert_auth.py
interact/interact6.py
interact/rc.py
pyinteract.egg-info/PKG-INFO
pyinteract.egg-info/SOURCES.txt
pyinteract.egg-info/dependency_links.txt
pyinteract.egg-info/requires.txt
pyinteract.egg-info/top_level.txt