Metadata-Version: 1.1
Name: pyinteract
Version: 0.7.4
Summary: A Python API for the SOAP Web Services offered by responsys.
Home-page: https://bitbucket.org/johannestaas/responsys_pyinteract
Author: Johan Nestaas, Mason Dixon
Author-email: johan.nestaas@oracle.com, mason.dixon@oracle.com
License: BSD
Keywords: responsys interact marketing oracle marketing cloud
Platform: UNKNOWN
Classifier: Development Status :: 4 - Beta
Classifier: Topic :: Utilities
Classifier: License :: OSI Approved :: BSD License
Classifier: Environment :: Web Environment
Classifier: Intended Audience :: Developers
Classifier: Operating System :: MacOS :: MacOS X
Classifier: Operating System :: Microsoft :: Windows
Classifier: Operating System :: POSIX
Classifier: Programming Language :: Python
Classifier: Topic :: Communications :: Email
Classifier: Topic :: Office/Business
